moanapi/__init__.py
moanapi/client.py
moanapi/apis/__init__.py
moanapi/apis/ai.py
moanapi/apis/bypass.py
moanapi/apis/eh.py
moanapi/apis/generative.py
moanapi/apis/roblox.py
moanapi/apis/tts.py
moanapi/apis/utility.py
moanapi-0.3.0.dist-info/licenses/LICENSE
moanapi-0.3.0.dist-info/METADATA
moanapi-0.3.0.dist-info/WHEEL
moanapi-0.3.0.dist-info/top_level.txt
moanapi-0.3.0.dist-info/RECORD
