Metadata-Version: 2.4
Name: moanapi
Version: 0.3.0
Summary: A dynamic, auto-updating Python wrapper for the Moan API suite.
Author-email: mineogo <venkatesh10year@gmail.com>
License: MIT License
Project-URL: Homepage, https://moanapi.ddns.net
Project-URL: Bug Tracker, https://moanapi.duckdns.net/module/report-bug
Classifier: Programming Language :: Python :: 3
Classifier: Operating System :: OS Independent
Classifier: Topic :: Software Development :: Libraries :: Python Modules
Classifier: Intended Audience :: Developers
Requires-Python: >=3.7
License-File: LICENSE
Requires-Dist: requests>=2.25.0
Dynamic: license-file
